venus_driver/__init__.py
venus_driver/driver.json
venus_driver/py.typed
venus_driver/venus_driver.py
orca_driver_venus-0.1.0.dist-info/LICENSE
orca_driver_venus-0.1.0.dist-info/METADATA
orca_driver_venus-0.1.0.dist-info/WHEEL
orca_driver_venus-0.1.0.dist-info/top_level.txt
orca_driver_venus-0.1.0.dist-info/RECORD
