Metadata-Version: 2.2
Name: orca-driver-venus
Version: 0.1.0
Summary: Hamilton Venus command line driver
Author-email: Cheshire Labs <support@cheshirelabs.io>
License: AGPL-3.0-only
Project-URL: Repository, https://github.com/Cheshire-Labs/orca-driver-venus
Classifier: Programming Language :: Python :: 3.10
Classifier: License :: OSI Approved :: GNU Affero General Public License v3
Classifier: Operating System :: OS Independent
Requires-Python: >=3.10
License-File: LICENSE
Requires-Dist: orca_interfaces>=0.1.0
Provides-Extra: dev
Requires-Dist: pytest>=7.3.1; extra == "dev"
Requires-Dist: types-setuptools; extra == "dev"
